cookies_clean/__init__.py
cookies_clean/main.py
cookies_clean-0.0.2.dist-info/LICENCE.txt
cookies_clean-0.0.2.dist-info/METADATA
cookies_clean-0.0.2.dist-info/WHEEL
cookies_clean-0.0.2.dist-info/top_level.txt
cookies_clean-0.0.2.dist-info/RECORD
