Metadata-Version: 2.1
Name: cookies-clean
Version: 0.0.2
Summary: Package created to clean your code up!
Home-page: http://cookiesservices.xyz/
Author: CookiesKush420
Author-email: callumgm20052005@gmail.com
License: MIT
Keywords: CleanConsole,printslow,getheaders,proxyscrape
Platform: UNKNOWN
Classifier: Development Status :: 5 - Production/Stable
Classifier: Intended Audience :: Education
Classifier: Operating System :: Microsoft :: Windows :: Windows 10
Classifier: License :: OSI Approved :: MIT License
Classifier: Programming Language :: Python :: 3.8
License-File: LICENCE.txt
Requires-Dist: requests
Requires-Dist: colorama
